zodable_sample_package_multiplatform/__init__.py
zodable_sample_package_multiplatform/py.typed
zodable_sample_package_multiplatform/digital/guimauve/example/MultiplatformType.py
zodable_sample_package_multiplatform/digital/guimauve/example/MultiplatformUser.py
zodable_sample_package_multiplatform-1.6.0.dist-info/METADATA
zodable_sample_package_multiplatform-1.6.0.dist-info/WHEEL
zodable_sample_package_multiplatform-1.6.0.dist-info/top_level.txt
zodable_sample_package_multiplatform-1.6.0.dist-info/RECORD
