Metadata-Version: 2.4
Name: zodable-sample-package-multiplatform
Version: 1.6.0
Summary: Auto-generated Pydantic project from Kotlin using guimauvedigital/zodable
Requires-Python: >=3.9
Requires-Dist: pydantic
Requires-Dist: uuid
